LICENSE
MANIFEST.in
README
SourceCodePro-Regular.otf
_fixure.h
_fontconfig.h
fc.py
fontconfig_cffi.py
setup.py
test_fc.py
fontconfig.egg-info/PKG-INFO
fontconfig.egg-info/SOURCES.txt
fontconfig.egg-info/dependency_links.txt
fontconfig.egg-info/not-zip-safe
fontconfig.egg-info/requires.txt
fontconfig.egg-info/top_level.txt