Metadata-Version: 1.1
Name: fontconfig
Version: 0.1
Summary: CFFI bindings for fontconfig
Home-page: https://bitbucket.org/gm/fontconfig
Author: Marco Giusti
Author-email: marco.giusti@posteo.de
License: MIT
Keywords: fontconfig,cffi
Platform: UNKNOWN
Classifier: Development Status :: 3 - Alpha
Classifier: Intended Audience :: Developers
Classifier: License :: OSI Approved :: MIT License
Classifier: Programming Language :: Python
Classifier: Programming Language :: Python :: 2
Classifier: Programming Language :: Python :: 2.7
Classifier: Topic :: Software Development :: Libraries
